pytest_evm/__init__.py
pytest_evm/exceptions.py
pytest_evm/fixtures.py
pytest_evm/hooks.py
pytest_evm/pytest.ini
pytest_evm/utils.py
pytest_evm-0.2.0.post2.dist-info/LICENSE
pytest_evm-0.2.0.post2.dist-info/METADATA
pytest_evm-0.2.0.post2.dist-info/WHEEL
pytest_evm-0.2.0.post2.dist-info/entry_points.txt
pytest_evm-0.2.0.post2.dist-info/RECORD
