Metadata-Version: 2.1
Name: pytest_evm
Version: 0.2.0.post2
Summary: The testing package containing tools to test Web3-based projects
Home-page: https://github.com/CrocoFactory/pytest-evm
License: MIT
Author: Alexey
Author-email: axbelenkov@gmail.com
Requires-Python: >=3.11,<4.0
Classifier: Development Status :: 4 - Beta
Classifier: Framework :: Pytest
Classifier: Intended Audience :: Developers
Classifier: License :: OSI Approved :: MIT License
Classifier: Operating System :: MacOS
Classifier: Operating System :: Microsoft :: Windows
Classifier: Programming Language :: Python :: 3
Classifier: Programming Language :: Python :: 3.11
Classifier: Programming Language :: Python :: 3.12
Classifier: Programming Language :: Python :: 3 :: Only
Classifier: Topic :: Software Development :: Libraries :: Python Modules
Classifier: Topic :: Software Development :: Testing
Provides-Extra: dotenv
Requires-Dist: evm-wallet (>=2.0.2,<3.0.0)
Requires-Dist: pytest (>=8.1.1,<9.0.0)
Requires-Dist: pytest-asyncio (>=0.23.6,<0.24.0)
Requires-Dist: python-dotenv (>=1.0.1,<2.0.0) ; extra == "dotenv"
Requires-Dist: web3 (>=6.12.0,<7.0.0)
Project-URL: Repository, https://github.com/CrocoFactory/pytest-evm
